Workbook

Sheet Тестовый портфель
A1: report_dttm | B1: discriminator | C1: deal_id | D1: currency_id | E1: start_principal_amt | F1: current_principal_amt | G1: deal_dttm | H1: maturity_dttm | I1: rate_type_cd | J1: interest_rate | K1: base_indicator_rate | L1: base_indicator | M1: interest_payment_rule_start_dttm | N1: interest_payment_rule_period_cd | O1: interest_payment_rule_day_num | P1: day_convention_cd | Q1: regular_payment_rule_start_dttm | R1: regular_payment_rule_period_cd | S1: regular_payment_rule_day_num | T1: repricing_rule_start_dttm | U1: repricing_rule_period_cd | V1: repricing_rule_day_num | W1: accrued_interest | X1: product | Y1: behavior_model_cd | Z1: interest_payment | AA1: principal_payment | AB1: repricing_dttm_schedule | AC1: repricing_dttm_rate_schedule | AD1: repricing_dttm_rate_schedule_fixed | AE1: cap_limit_interest_rate | AF1: floor_limit_interest_rate | AG1: sub_rate_type_cd | AH1: sub_interest_rate | AI1: sub_float_indicator | AJ1: sub_payment_rule_period_cd | AK1: sub_payment_rule_day_num | AL1: sub_payment_rule_start_dttm | AM1: sub_repricing_rule_start_dttm | AN1: sub_repricing_rule_period_cd | AO1: sub_repricing_rule_day_num | AP1: sub_cap_limit_interest_rate | AQ1: sub_floor_limit_interest_rate | AR1: sub_coeff_index | AS1: deal_report_dttm | AT1: sub_repricing_rule_first_event_flg | AU1: indicator_lag_cd | AV1: sub_indicator_lag_cd | AW1: Столбец1
A2: 44804 | B2: ANN | C2: 1 | D2: RUB | F2: 3646037.9 | G2: 44004 | H2: 54954 | I2: FIXED | J2: 0.075 | P2: ACT/ACT | Q2: 44004 | R2: 1M | Y2: PREPAYMENT_CONSUMER | AS2: 44804
A3: 44804 | B3: ANN | C3: 5 | D3: RUB | F3: 4800112.5 | G3: 44182 | H3: 47772 | I3: FIXED | J3: 0.07426415 | P3: ACT/ACT | Q3: 44182 | R3: 1M | Y3: PREPAYMENT_MORTGAGE | AS3: 44804
A4: 44804 | B4: ANN | C4: 9 | D4: RUB | F4: 290027.78 | G4: 41879 | H4: 45599 | I4: FIXED | J4: 0.13 | M4: 41581 | N4: 1M | O4: 3 | P4: ACT/ACT ISDA | Q4: 41581 | R4: 1M | S4: 3 | X4: mortgage | Y4: PREPAYMENT_MR8_CRED | AS4: 44804
A5: 44804 | B5: SIMPLE | C5: 16 | D5: RUB | F5: 1047077.3 | G5: 44158 | H5: 45046 | I5: FIXED | J5: 0.061 | M5: 44158 | N5: 1M | O5: 7 | P5: ACT/ACT ISDA | X5: mortgage | Y5: PREPAYMENT_MORTGAGE | AA5: 2022-12-31,250000.0 2023-01-31,250000.0 2023-02-28,250000.0 2023-04-30,297077.3 | AS5: 44804
A6: 44804 | B6: SIMPLE | C6: 19 | D6: RUB | F6: 1047077.3 | G6: 44158 | H6: 45046 | I6: FIXED | J6: 0.061 | P6: ACT/ACT ISDA | X6: loan_auto | Y6: PREPAYMENT_AUTO | Z6: 2022-08-14 2022-11-14 2022-12-15 2023-01-15 2023-02-15 2023-04-15 | AA6: 2022-12-31,250000.0 2023-01-31,250000.0 2023-02-28,250000.0 2023-04-30,297077.3 | AS6: 44804
A7: 44804 | B7: ANN | C7: 28 | D7: RUB | F7: 270000 | G7: 44671 | H7: 45493 | I7: FIXED | J7: 0.119 | M7: 44671 | N7: 1M | O7: 20 | P7: ACT/ACT ISDA | Q7: 44671 | R7: 1M | S7: 20 | X7: loans_corporate | AS7: 44804
A8: 44804 | B8: RGM | C8: 29 | D8: RUB | F8: 270000 | G8: 44671 | H8: 45493 | I8: FIXED | J8: 0.119 | M8: 44671 | N8: 1M | O8: 20 | P8: ACT/ACT ISDA | Q8: 44671 | R8: 1M | S8: 20 | X8: loans_corporate | AS8: 44804
A9: 44804 | B9: SIMPLE | C9: 33 | D9: RUB | E9: 500000 | F9: 500000 | G9: 44774 | H9: 44927 | I9: FLOAT | J9: 0.05 | L9: CBKEY1M | M9: 44774 | N9: 1M | O9: 1 | P9: ACT/365 | T9: 44713 | U9: 2M | AA9: 2022-09-01,100000.0 2022-10-01,100000.0 2022-11-01,100000.0 2022-12-01,100000.0 2023-01-01,100000.0 | AS9: 44804
A10: 44804 | B10: SIMPLE | C10: 35 | D10: RUB | E10: 500000 | F10: 500000 | G10: 44774 | H10: 44927 | I10: FLOAT | J10: 0.05 | L10: CBKEY1M | M10: 44774 | N10: 1M | O10: 1 | P10: ACT/365 | T10: 44742 | U10: 2M | V10: -1 | AS10: 44804
A11: 44804 | B11: SIMPLE | C11: 44 | D11: RUB | F11: 224204.19 | G11: 44074 | H11: 44925 | I11: FIXED | J11: 0.09 | P11: ACT/ACT ISDA | W11: 0 | X11: loans_corporate | Z11: 2022-09-30 2022-10-31 2022-11-30 2022-12-30 2022-08-31 | AA11: 2022-09-30,55424.4 2022-10-31,55840.08 2022-11-30,56258.88 2022-12-30,56680.82 | AB11: 44804 | AD11: 2022-08-31,0.09 | AS11: 44804

Sheet Портфель 5 сделок
A1: Сделка | B1: Долг | C1: Проценты | D1: Денежный поток | E1: NPV базовая | F1: NPV стрессовая | G1: dNPV
A2: 1 | B2: ='1 сделка'!$F$3 -> 3646037.9 | C2: =SUM('1 сделка'!F19:F352) -> 5065848.1 | D2: =SUM('1 сделка'!G19:G352) -> 8696465.5 | E2: ='1 сделка'!K353 -> 2056999.5 | F2: ='1 сделка'!M353 -> 1892477.1 | G2: ='1 сделка'!N353 -> -164522.41
A3: 16 | B3: =#REF! -> #REF! | C3: =SUM(#REF!) -> #REF! | D3: =SUM(#REF!) -> #REF! | E3: =#REF! -> #REF! | F3: =#REF! -> #REF! | G3: =#REF! -> #REF!
A4: 29 | B4: =#REF! -> #REF! | C4: =SUM(#REF!) -> #REF! | D4: =SUM(#REF!) -> #REF! | E4: =#REF! -> #REF! | F4: =#REF! -> #REF! | G4: =#REF! -> #REF!
A5: 33 | B5: =#REF! -> #REF! | C5: =SUM(#REF!) -> #REF! | D5: =SUM(#REF!) -> #REF! | E5: =#REF! -> #REF! | F5: =#REF! -> #REF! | G5: =#REF! -> #REF!
A6: 44 | B6: =#REF! -> #REF! | C6: =SUM(#REF!) -> #REF! | D6: =SUM(#REF!) -> #REF! | E6: =#REF! -> #REF! | F6: =#REF! -> #REF! | G6: =#REF! -> #REF!
A7: ИТОГО | B7: =SUM(B2:B6) -> #REF! | C7: =SUM(C2:C6) -> #REF! | D7: =SUM(D2:D6) -> #REF! | E7: =SUM(E2:E6) -> #REF! | F7: =SUM(F2:F6) -> #REF! | G7: =SUM(G2:G6) -> #REF!

Sheet КС ЦБ
A1: Источник: Банк России. Ключевая ставка.
A2: https://www.cbr.ru/hd_base/KeyRate/
A3: История по 15.10.2026
A6: Дата | B6: Ключевая ставка
A7: 43833 | B7: 0.0625
A8: 43836 | B8: 0.0625
A9: 43838 | B9: 0.0625
A10: 43839 | B10: 0.0625
A11: 43840 | B11: 0.0625
A12: 43843 | B12: 0.0625
A13: 43844 | B13: 0.0625
A14: 43845 | B14: 0.0625
A15: 43846 | B15: 0.0625
A16: 43847 | B16: 0.0625
A17: 43850 | B17: 0.0625
A18: 43851 | B18: 0.0625
... A1727: 46310 | B1727: 0.14

Sheet Тестовые сделки
A1: report_dttm | B1: discriminator | C1: deal_id | D1: currency_id | E1: start_principal_amt | F1: current_principal_amt | G1: deal_dttm | H1: maturity_dttm | I1: rate_type_cd | J1: interest_rate | K1: base_indicator_rate | L1: base_indicator | M1: interest_payment_rule_start_dttm | N1: interest_payment_rule_period_cd | O1: interest_payment_rule_day_num | P1: day_convention_cd | Q1: regular_payment_rule_start_dttm | R1: regular_payment_rule_period_cd | S1: regular_payment_rule_day_num | T1: repricing_rule_start_dttm | U1: repricing_rule_period_cd | V1: repricing_rule_day_num | W1: accrued_interest | X1: product | Y1: behavior_model_cd | Z1: interest_payment | AA1: principal_payment | AB1: repricing_dttm_schedule | AC1: repricing_dttm_rate_schedule | AD1: repricing_dttm_rate_schedule_fixed | AE1: cap_limit_interest_rate | AF1: floor_limit_interest_rate | AG1: sub_rate_type_cd | AH1: sub_interest_rate | AI1: sub_float_indicator | AJ1: sub_payment_rule_period_cd | AK1: sub_payment_rule_day_num | AL1: sub_payment_rule_start_dttm | AM1: sub_repricing_rule_start_dttm | AN1: sub_repricing_rule_period_cd | AO1: sub_repricing_rule_day_num | AP1: sub_cap_limit_interest_rate | AQ1: sub_floor_limit_interest_rate | AR1: sub_coeff_index | AS1: deal_report_dttm | AT1: sub_repricing_rule_first_event_flg | AU1: indicator_lag_cd | AV1: sub_indicator_lag_cd | AW1: Столбец1
A2: Дата, на которую выполняется расчет | B2: Код, по которому выбирается способ построения платежей | C2: Номер сделки | E2: Первоначальная сумма основного долга | F2: Остаток основного долга на дату расчёта | G2: Дата начала сделки | H2: Дата окончания сделки | J2: Процентная ставка | L2: код базового процентного индикатора, к которому привязана плавающая ставка сделки | M2: Начальная дата правила выплаты процентов | N2: Периодичность выплаты процентов | O2: День месяца для выплаты | P2: правило подсчёта времени для начисления процентов | Q2: Начальная дата правила, от которой строится расписание регулярных платежей. | R2: Периодичность регулярных платежей | U2: код периодичности пересмотра процентной ставки по сделке | X2: категория банковского продукта, к которому относится сделка | Y2: код модели поведения клиентов | Z2: Явно перечисленные даты выплаты процентов | AA2: Явно перечисленные даты и суммы возврата основного долга
A3: 44804 | B3: ANN | C3: 1 | D3: RUB | F3: 3646037.9 | G3: 44004 | H3: 54954 | I3: FIXED | J3: 0.075 | P3: ACT/ACT | Q3: 44004 | R3: 1M | Y3: PREPAYMENT_CONSUMER | AS3: 44804
A4: 44804 | B4: RGM | C4: 2 | D4: RUB | F4: 3646037.9 | G4: 44004 | H4: 54954 | I4: FIXED | J4: 0.075 | P4: ACT/ACT | Q4: 44004 | R4: 1M | Y4: PREPAYMENT_CONSUMER | AS4: 44804
A5: 44804 | B5: ANN | C5: 3 | D5: RUB | F5: 4800112.5 | G5: 44182 | H5: 47680 | I5: FIXED | J5: 0.07426415 | P5: ACT/ACT | Q5: 44182 | R5: 1M | Y5: PREPAYMENT_MORTGAGE | AS5: 44804
A6: 44804 | B6: RGM | C6: 4 | D6: RUB | F6: 3646037.9 | G6: 44096 | H6: 55046 | I6: FIXED | J6: 0.075 | M6: 44096 | N6: 1M | P6: ACT/ACT | Q6: 44096 | R6: 1M | Y6: PREPAYMENT_CONSUMER | AS6: 44804
A7: 44804 | B7: ANN | C7: 5 | D7: RUB | F7: 4800112.5 | G7: 44182 | H7: 47772 | I7: FIXED | J7: 0.07426415 | P7: ACT/ACT | Q7: 44182 | R7: 1M | Y7: PREPAYMENT_MORTGAGE | AS7: 44804
A8: 44804 | B8: RGM | C8: 6 | D8: RUB | F8: 3646037.9 | G8: 44096 | H8: 55046 | I8: FIXED | J8: 0.075 | M8: 44096 | N8: 1M | P8: ACT/ACT | Q8: 44096 | R8: 1M | Y8: PREPAYMENT_MORTGAGE | AS8: 44804
A9: 44804 | B9: ANN | C9: 7 | D9: RUB | F9: 349553.63 | G9: 43619 | H9: 44909 | I9: FIXED | J9: 0.15 | M9: 43448 | N9: 1M | O9: 14 | P9: ACT/ACT ISDA | Q9: 43448 | R9: 1M | S9: 14 | X9: car_loans | Y9: PREPAYMENT_AUTO | AS9: 44804
A10: 44804 | B10: ANN | C10: 8 | D10: RUB | F10: 60709.45 | G10: 43859 | H10: 44969 | I10: FIXED | J10: 0.1 | M10: 43508 | N10: 1M | O10: 12 | P10: ACT/ACT ISDA | Q10: 43508 | R10: 1M | S10: 12 | X10: consumer_loans | Y10: PREPAYMENT_CONSUMER | AS10: 44804
A11: 44804 | B11: ANN | C11: 9 | D11: RUB | F11: 290027.78 | G11: 41879 | H11: 45599 | I11: FIXED | J11: 0.13 | M11: 41581 | N11: 1M | O11: 3 | P11: ACT/ACT ISDA | Q11: 41581 | R11: 1M | S11: 3 | X11: mortgage | Y11: PREPAYMENT_MR8_CRED | AS11: 44804
A12: 44804 | B12: ANN | C12: 10 | D12: RUB | F12: 11061796 | G12: 43949 | H12: 49109 | I12: FIXED | J12: 0.08 | M12: 43630 | N12: 1M | O12: 14 | P12: ACT/ACT ISDA | Q12: 43630 | R12: 1M | S12: 14 | X12: mortgage | Y12: PREPAYMENT_MR8_CRED | AS12: 44804
A13: 44804 | B13: RGM | C13: 11 | D13: RUB | F13: 349553.63 | G13: 43619 | H13: 44909 | I13: FIXED | J13: 0.15 | M13: 43448 | N13: 1M | O13: 14 | P13: ACT/ACT ISDA | Q13: 43448 | R13: 1M | S13: 14 | X13: car_loans | Y13: PREPAYMENT_AUTO | AS13: 44804
A14: 44804 | B14: RGM | C14: 12 | D14: RUB | F14: 60709.45 | G14: 43859 | H14: 44969 | I14: FIXED | J14: 0.1 | M14: 43508 | N14: 1M | O14: 12 | P14: ACT/ACT ISDA | Q14: 43508 | R14: 1M | S14: 12 | X14: consumer_loans | Y14: PREPAYMENT_CONSUMER | AS14: 44804
A15: 44804 | B15: RGM | C15: 13 | D15: RUB | E15: 0 | F15: 1047077.3 | G15: 44158 | H15: 45046 | I15: FIXED | J15: 0.06 | M15: 44581 | N15: 1M | O15: 7 | P15: ACT/ACT ISDA | Q15: 44581 | R15: 1M | S15: 7 | T15: 44581 | X15: mortgage | Y15: PREPAYMENT_MORTGAGE | AS15: 44804
A16: 44804 | B16: RGM | C16: 14 | D16: RUB | F16: 1047077.3 | G16: 44158 | H16: 45046 | I16: FIXED | J16: 0.061 | M16: 44158 | N16: 1M | O16: 14 | P16: ACT/ACT ISDA | Q16: 44158 | R16: 1M | S16: 14 | Y16: PREPAYMENT_MR8_CRED | AS16: 44804
A17: 44804 | B17: SIMPLE | C17: 15 | D17: RUB | F17: -1896648.9 | G17: 44789 | H17: 44999 | I17: FIXED | J17: 0.04 | M17: 44789 | N17: 1M | O17: 14 | P17: ACT/ACT ISDA | R17: ENDDATE | X17: deposits_individual | Y17: PREPAYMENT_MR8_DEP | AS17: 44804
A18: 44804 | B18: SIMPLE | C18: 16 | D18: RUB | F18: 1047077.3 | G18: 44158 | H18: 45046 | I18: FIXED | J18: 0.061 | M18: 44158 | N18: 1M | O18: 7 | P18: ACT/ACT ISDA | X18: mortgage | Y18: PREPAYMENT_MORTGAGE | AA18: 2022-12-31,250000.0 2023-01-31,250000.0 2023-02-28,250000.0 2023-04-30,297077.3 | AS18: 44804
A19: 44804 | B19: SIMPLE | C19: 17 | D19: RUB | F19: 1047077.3 | G19: 44158 | H19: 45046 | I19: FIXED | J19: 0.061 | M19: 44158 | N19: 1M | O19: 7 | P19: ACT/ACT ISDA | X19: consumer | Y19: PREPAYMENT_CONSUMER | AA19: 2022-12-31,250000.0 2023-01-31,250000.0 2023-02-28,250000.0 2023-04-30,297077.3 | AS19: 44804
A20: 44804 | B20: SIMPLE | C20: 18 | D20: RUB | F20: 1047077.3 | G20: 44158 | H20: 45046 | I20: FIXED | J20: 0.061 | M20: 44158 | N20: 1M | O20: 7 | P20: ACT/ACT ISDA | X20: loan_auto | Y20: PREPAYMENT_AUTO | AA20: 2022-12-31,250000.0 2023-01-31,250000.0 2023-02-28,250000.0 2023-04-30,297077.3 | AS20: 44804
A21: 44804 | B21: SIMPLE | C21: 19 | D21: RUB | F21: 1047077.3 | G21: 44158 | H21: 45046 | I21: FIXED | J21: 0.061 | P21: ACT/ACT ISDA | X21: loan_auto | Y21: PREPAYMENT_AUTO | Z21: 2022-08-14 2022-11-14 2022-12-15 2023-01-15 2023-02-15 2023-04-15 | AA21: 2022-12-31,250000.0 2023-01-31,250000.0 2023-02-28,250000.0 2023-04-30,297077.3 | AS21: 44804
A22: 44804 | B22: SIMPLE | C22: 20 | D22: RUB | F22: 1047077.3 | G22: 44158 | H22: 45046 | I22: FIXED | J22: 0.061 | M22: 44158 | N22: 1M | O22: 7 | P22: ACT/ACT ISDA | Y22: PREPAYMENT_MR8_CRED | AA22: 2022-12-31,250000 2023-01-31,250000 2023-02-28,250000 2023-04-30,356179 | AS22: 44804
A23: 44804 | B23: SIMPLE | C23: 21 | D23: RUB | F23: 1047077.3 | G23: 44158 | H23: 45046 | I23: FIXED | J23: 0.061 | M23: 44158 | N23: 1M | O23: 7 | P23: ACT/ACT ISDA | R23: ENDDATE | Y23: PREPAYMENT_MR8_CRED | AS23: 44804
A24: 44804 | B24: RGM | C24: 22 | D24: RUB | E24: 0 | F24: 1000000 | G24: 44581 | H24: 45046 | I24: FLOAT | J24: 0.11 | L24: CBKEY1M | M24: 44581 | N24: 1M | O24: 10 | P24: ACT/ACT ISDA | Q24: 44581 | R24: 1M | S24: 20 | T24: 44581 | U24: 1M | V24: 15 | X24: mortgage | AE24: 1 | AF24: 0 | AS24: 44804
A25: 44804 | B25: RGM | C25: 23 | D25: RUB | E25: 0 | F25: 1000000 | G25: 44581 | H25: 45077 | I25: FLOAT | J25: 0.11 | K25: 0 | L25: CBKEY1M | M25: 44581 | N25: 1M | O25: 30 | P25: ACT/ACT ISDA | Q25: 44581 | R25: 1M | S25: 30 | T25: 44581 | U25: 1M | V25: 15 | X25: mortgage | Y25: PREPAYMENT_MR8_CRED | AE25: 1 | AF25: 0 | AS25: 44804
A26: 44804 | B26: RGM | C26: 24 | D26: RUB | E26: 0 | F26: 1093204.6 | G26: 42809 | H26: 45063 | I26: FIXED | J26: 0.1 | M26: 42809 | N26: 1M | O26: 7 | P26: ACT/ACT ISDA | Q26: 42809 | R26: 1M | S26: 17 | X26: mortgage | Y26: PREPAYMENT_MORTGAGE | AE26: 0.4 | AF26: 0 | AS26: 44804
A27: 44804 | B27: SIMPLE | C27: 25 | D27: RUB | E27: 500000 | F27: 500000 | G27: 44774 | H27: 44927 | I27: FLOAT | J27: 0.05 | L27: CBKEY1M | M27: 44774 | N27: 1M | O27: 1 | P27: ACT/365 | Q27: 44774 | R27: ENDDATE | AE27: 0.1 | AF27: 0.06 | AS27: 44804
A28: 44804 | B28: ANN | C28: 26 | D28: RUB | F28: 2493753.9 | G28: 44550 | H28: 46507 | I28: FIXED | J28: 0.109 | M28: 44550 | N28: 1M | O28: 30 | P28: ACT/ACT ISDA | Q28: 44550 | R28: 1M | S28: 30 | X28: mortgage | AS28: 44804
A29: 44804 | B29: RGM | C29: 27 | D29: RUB | F29: 3605963.1 | G29: 43000 | H29: 45555 | I29: FIXED | J29: 0.119 | M29: 43000 | N29: 1M | O29: 20 | P29: ACT/ACT ISDA | Q29: 42633 | R29: 1M | S29: 20 | X29: loans_corporate | AS29: 44804
A30: 44804 | B30: ANN | C30: 28 | D30: RUB | F30: 270000 | G30: 44671 | H30: 45493 | I30: FIXED | J30: 0.119 | M30: 44671 | N30: 1M | O30: 20 | P30: ACT/ACT ISDA | Q30: 44671 | R30: 1M | S30: 20 | X30: loans_corporate | AS30: 44804
A31: 44804 | B31: RGM | C31: 29 | D31: RUB | F31: 270000 | G31: 44671 | H31: 45493 | I31: FIXED | J31: 0.119 | M31: 44671 | N31: 1M | O31: 20 | P31: ACT/ACT ISDA | Q31: 44671 | R31: 1M | S31: 20 | X31: loans_corporate | AS31: 44804
A32: 44804 | B32: SIMPLE | C32: 30 | D32: RUB | E32: 500000 | F32: 500000 | G32: 44774 | H32: 44927 | I32: FLOAT | J32: 0.05 | L32: CBKEY1M | M32: 44774 | N32: 45D | P32: ACT/365 | T32: 44729 | U32: 45D | AA32: 2022-09-01,100000.0 2022-10-01,100000.0 2022-11-01,100000.0 2022-12-01,100000.0 2023-01-01,100000.0 | AS32: 44804
A33: 44804 | B33: SIMPLE | C33: 31 | D33: RUB | E33: 500000 | F33: 500000 | G33: 44774 | H33: 44927 | I33: FLOAT | J33: 0.05 | L33: CBKEY1M | M33: 44774 | N33: 1M | O33: 1 | P33: ACT/365 | T33: 44729 | U33: 45D | AA33: 2022-09-01,100000.0 2022-10-01,100000.0 2022-11-01,100000.0 2022-12-01,100000.0 2023-01-01,100000.0 | AS33: 44804
A34: 44804 | B34: SIMPLE | C34: 32 | D34: USD | E34: 500000 | F34: 500000 | G34: 44774 | H34: 44927 | I34: FLOAT | J34: 0.05 | L34: CBKEY1M | M34: 44774 | N34: 1M | O34: 1 | P34: ACT/365 | T34: 44743 | U34: 1M | AA34: 2022-09-01,100000.0 2022-10-01,100000.0 2022-11-01,100000.0 2022-12-01,100000.0 2023-01-01,100000.0 | AS34: 44804
A35: 44804 | B35: SIMPLE | C35: 33 | D35: RUB | E35: 500000 | F35: 500000 | G35: 44774 | H35: 44927 | I35: FLOAT | J35: 0.05 | L35: CBKEY1M | M35: 44774 | N35: 1M | O35: 1 | P35: ACT/365 | T35: 44713 | U35: 2M | AA35: 2022-09-01,100000.0 2022-10-01,100000.0 2022-11-01,100000.0 2022-12-01,100000.0 2023-01-01,100000.0 | AS35: 44804
A36: 44804 | B36: SIMPLE | C36: 34 | D36: RUB | E36: 500000 | F36: 500000 | G36: 44774 | H36: 44927 | I36: FLOAT | J36: 0.05 | L36: CBKEY1M | M36: 44774 | N36: 1M | O36: 1 | P36: ACT/365 | AA36: 2022-09-01,100000.0 2022-10-01,100000.0 2022-11-01,100000.0 2022-12-01,100000.0 2023-01-01,100000.0 | AS36: 44804
A37: 44804 | B37: SIMPLE | C37: 35 | D37: RUB | E37: 500000 | F37: 500000 | G37: 44774 | H37: 44927 | I37: FLOAT | J37: 0.05 | L37: CBKEY1M | M37: 44774 | N37: 1M | O37: 1 | P37: ACT/365 | T37: 44742 | U37: 2M | V37: -1 | AS37: 44804
A38: 44804 | B38: SIMPLE | C38: 36 | D38: RUB | E38: 500000 | F38: 500000 | G38: 44774 | H38: 44927 | I38: FLOAT | J38: 0.05 | L38: CBKEY1M | M38: 44774 | N38: ENDDATE | P38: ACT/365 | Q38: 44774 | R38: ENDDATE | W38: 1000 | AS38: 44804
A39: 44804 | B39: SIMPLE | C39: 37 | D39: RUB | E39: 500000 | F39: 500000 | G39: 44774 | H39: 44927 | I39: FLOAT | J39: 0.05 | L39: CBKEY1M | M39: 44774 | N39: ENDDATE | P39: ACT/365 | Q39: 44774 | R39: ENDDATE | T39: 44713 | U39: 2M | W39: 1000 | AS39: 44804
A40: 44804 | B40: SIMPLE | C40: 38 | D40: RUB | E40: 500000 | F40: 500000 | G40: 44774 | H40: 44927 | I40: FLOAT | J40: 0.05 | L40: CBKEY1M | M40: 44774 | N40: ENDDATE | P40: ACT/365 | Q40: 44774 | R40: ENDDATE | T40: 44621 | U40: 5M | W40: 1000 | AS40: 44804
A41: 44804 | B41: SIMPLE | C41: 39 | D41: RUB | E41: 500000 | F41: 500000 | G41: 44774 | H41: 44927 | I41: FLOAT | J41: 0.05 | L41: CBKEY1M | M41: 44774 | N41: ENDDATE | P41: ACT/365 | Q41: 44774 | R41: ENDDATE | T41: 44729 | U41: 45D | W41: 1000 | AS41: 44804
A42: 44804 | B42: SIMPLE | C42: 40 | D42: RUB | E42: 500000 | F42: 500000 | G42: 44774 | H42: 44927 | I42: FLOAT | J42: 0.05 | L42: CBKEY1M | M42: 44774 | N42: ENDDATE | P42: ACT/365 | Q42: 44774 | R42: ENDDATE | T42: 44621 | U42: 153D | W42: 1000 | AS42: 44804
A43: 44804 | B43: SIMPLE | C43: 41 | D43: RUB | F43: -12000000 | G43: 44616 | H43: 44919 | I43: FLOAT | J43: 0.05 | L43: CBKEY1M | M43: 44673 | N43: 1M | P43: ACT/ACT ISDA | R43: ENDDATE | T43: 44743 | U43: 1M | V43: 1 | AS43: 44804
A44: 44804 | B44: RGM | C44: 42 | D44: RUB | F44: 500000 | G44: 44774 | H44: 44927 | I44: FLOAT | J44: 0.04 | K44: 0.08 | L44: CBKEY1M | M44: 44774 | N44: 1M | O44: 1 | P44: ACT/365 | AB44: 2022-07-15 2022-09-15 2022-12-15 | AS44: 44804
A45: 44804 | B45: RGM | C45: 43 | D45: RUB | F45: 500000 | G45: 44774 | H45: 44927 | I45: FLOAT | J45: 0.04 | K45: 0.08 | L45: CBKEY1M | P45: ACT/365 | T45: 44629 | U45: 3M | V45: 9 | AB45: 2022-07-15 2022-09-15 2022-12-15 | AS45: 44804
A46: 44804 | B46: SIMPLE | C46: 44 | D46: RUB | F46: 224204.19 | G46: 44074 | H46: 44925 | I46: FIXED | J46: 0.09 | P46: ACT/ACT ISDA | W46: 0 | X46: loans_corporate | Z46: 2022-09-30 2022-10-31 2022-11-30 2022-12-30 2022-08-31 | AA46: 2022-09-30,55424.4 2022-10-31,55840.08 2022-11-30,56258.88 2022-12-30,56680.82 | AB46: 44804 | AD46: 2022-08-31,0.09 | AS46: 44804
A47: 44804 | B47: SIMPLE | C47: 45 | D47: RUB | F47: 156750 | G47: 44698 | H47: 44935 | I47: FLOAT | J47: 0.05 | K47: 0.08 | L47: CBKEY1M | P47: ACT/ACT ISDA | X47: loans_corporate | Z47: 2023-01-09 2022-11-30 2022-12-30 2022-09-30 2022-10-31 2022-08-31 | AA47: 2022-11-30,52250.0 2023-01-09,52250.0 2022-10-31,52250.0 | AB47: 44895 | AS47: 44804
A48: 44804 | B48: SIMPLE | C48: 46 | D48: RUB | F48: 156750 | G48: 44698 | H48: 44935 | I48: FLOAT | J48: 0.05 | K48: 0.08 | L48: CBKEY1M | P48: ACT/ACT ISDA | W48: 0 | X48: loans_corporate | Z48: 2022-08-31 2022-09-30 2022-10-31 2022-11-30 2022-12-30 2023-01-09 | AA48: 2022-10-31,52250.0 2022-11-30,52250.0 2023-01-09,52250.0 | AB48: 2022-08-31 2022-09-30 2022-10-30 2022-11-29 2022-12-29 | AD48: 2022-08-31,0.05 | AS48: 44804
A49: 44804 | B49: ANN | C49: 47 | D49: RUB | F49: 379878.38 | G49: 44010 | H49: 45090 | I49: FIXED | J49: 0.07 | M49: 43629 | N49: 1M | O49: 13 | P49: ACT/ACT ISDA | Q49: 43629 | R49: 1M | S49: 13 | X49: consumer_loans | Y49: PREPAYMENT_CONSUMER | AG49: FLOAT | AH49: 0.075 | AI49: CBKEY1M | AJ49: 1M | AK49: 13 | AL49: 44010 | AM49: 44010 | AN49: 1M | AO49: -1 | AS49: 44804 | AT49: 1
A50: 44804 | B50: ANN | C50: 48 | D50: RUB | F50: -379878.38 | G50: 44010 | H50: 45090 | I50: FIXED | J50: 0.07146796 | M50: 43629 | N50: 1M | O50: 13 | P50: ACT/ACT ISDA | Q50: 43629 | R50: 1M | S50: 13 | X50: consumer_loans | Y50: PREPAYMENT_CONSUMER | AG50: FLOAT | AH50: 0.075 | AI50: CBKEY1M | AJ50: 2M | AK50: 20 | AL50: 44010 | AM50: 44010 | AN50: 2M | AO50: -1 | AS50: 44804 | AT50: 1
A51: 44804 | B51: ANN | C51: 49 | D51: RUB | F51: 379878.38 | G51: 44010 | H51: 45090 | I51: FIXED | J51: 0.07146796 | M51: 43629 | N51: 1M | O51: 13 | P51: ACT/ACT ISDA | Q51: 43629 | R51: 1M | S51: 13 | X51: consumer_loans | Y51: PREPAYMENT_CONSUMER | AG51: FLOAT | AH51: 0.075 | AI51: CBKEY1M | AJ51: 2M | AK51: 20 | AL51: 44010 | AM51: 44010 | AN51: 2M | AO51: -1 | AS51: 44804 | AT51: 1
A52: 44804 | B52: ANN | C52: 50 | D52: RUB | F52: 379878.38 | G52: 44740 | H52: 45090 | I52: FIXED | J52: 0.07146796 | M52: 44740 | N52: 1M | O52: 13 | P52: ACT/ACT ISDA | Q52: 44740 | R52: 1M | S52: 13 | X52: consumer_loans | Y52: PREPAYMENT_CONSUMER | AG52: FLOAT | AH52: 0.075 | AI52: CBKEY1M | AJ52: 1M | AK52: 20 | AL52: 44866 | AM52: 44740 | AN52: 2M | AO52: -1 | AS52: 44804 | AT52: 1
A53: 44804 | B53: RGM | C53: 51 | D53: RUB | F53: 1047077.3 | G53: 44158 | H53: 45046 | I53: FLOAT | J53: 0.061 | L53: CBKEY1M | M53: 44158 | N53: 1M | O53: 7 | P53: ACT/ACT ISDA | Q53: 44158 | R53: 1M | S53: 7 | T53: 44158 | U53: 1M | V53: 7 | X53: product | AG53: FLOAT | AH53: 0.031 | AI53: CBKEY1M | AJ53: 1M | AK53: 7 | AL53: 44158 | AM53: 44158 | AN53: 1M | AO53: -1 | AS53: 44804 | AT53: 1 | AU53: -1M | AV53: -1M
A54: 44804 | B54: RGM | C54: 52 | D54: RUB | F54: 1047077.3 | G54: 44158 | H54: 45046 | I54: FIXED | J54: 0.061 | K54: 0 | M54: 44158 | N54: 1M | O54: 7 | P54: ACT/ACT ISDA | Q54: 44158 | R54: 1M | S54: 7 | X54: product | AG54: FIXED | AH54: 0.031 | AJ54: 1M | AK54: 7 | AL54: 44158 | AM54: 44158 | AN54: 1M | AO54: -1 | AR54: 0.9 | AS54: 44804 | AT54: 1
A55: 44804 | B55: RGM | C55: 53 | D55: RUB | F55: 1047077.3 | G55: 44158 | H55: 45046 | I55: FIXED | J55: 0.061 | K55: 0 | M55: 44158 | N55: 1M | O55: 7 | P55: ACT/ACT ISDA | Q55: 44158 | R55: 1M | S55: 7 | X55: product | AG55: FLOAT | AH55: 0.031 | AI55: CBKEY1M | AJ55: 1M | AK55: 7 | AL55: 44158 | AM55: 44158 | AN55: 1M | AO55: -1 | AR55: 0.9 | AS55: 44804 | AT55: 1
A56: 44804 | B56: SIMPLE | C56: 54 | D56: RUB | E56: 9020721.2 | F56: 9020721.2 | G56: 44105 | H56: 47402 | I56: FIXED | J56: 0.085 | K56: 0 | P56: ACT/ACT | Z56: 2022-09-30 2022-10-31 2022-12-02 2023-01-09 2023-01-31 2023-02-28 2023-03-31 | AA56: 2022-10-31,117583.73 2022-12-02,116362.61 2023-01-09,104933.2 2023-01-31,138048.42 2023-02-28,126817.79 2023-03-31,121764.35 2023-04-30,124575.16 | AG56: FIXED | AH56: 0.035 | AI56: CBKEY1M | AJ56: 1M | AL56: 43840 | AM56: 43840 | AN56: 1M | AO56: 1 | AQ56: 0 | AR56: 0 | AS56: 44804 | AT56: 1
A57: 44804 | B57: SIMPLE | C57: 55 | D57: RUB | E57: 9020721.2 | F57: 9020721.2 | G57: 43851 | H57: 45842 | I57: FLOAT | J57: 0.085 | L57: CBKEY1M | P57: ACT/ACT | Z57: 2025-04-30 2025-06-30 2025-06-02 2025-04-30 | AA57: 2025-07-04,9020721.21 | AG57: FLOAT | AH57: 0.035 | AI57: CBKEY1M | AJ57: 1M | AL57: 43851 | AM57: 43851 | AN57: 1M | AO57: 1 | AQ57: 0 | AR57: 0.5 | AS57: 44804 | AT57: 1

Sheet 1 сделка
A1: report_dttm | B1: discriminator | C1: deal_id | D1: currency_id | E1: start_principal_amt | F1: current_principal_amt | G1: deal_dttm | H1: maturity_dttm | I1: rate_type_cd | J1: interest_rate | K1: base_indicator_rate | L1: base_indicator | M1: interest_payment_rule_start_dttm | N1: interest_payment_rule_period_cd | O1: interest_payment_rule_day_num | P1: day_convention_cd | Q1: regular_payment_rule_start_dttm | R1: regular_payment_rule_period_cd | S1: regular_payment_rule_day_num | T1: repricing_rule_start_dttm | U1: repricing_rule_period_cd | V1: repricing_rule_day_num | W1: accrued_interest | X1: product | Y1: behavior_model_cd | Z1: interest_payment | AA1: principal_payment | AB1: repricing_dttm_schedule | AC1: repricing_dttm_rate_schedule | AD1: repricing_dttm_rate_schedule_fixed | AE1: cap_limit_interest_rate | AF1: floor_limit_interest_rate | AG1: sub_rate_type_cd | AH1: sub_interest_rate | AI1: sub_float_indicator | AJ1: sub_payment_rule_period_cd | AK1: sub_payment_rule_day_num | AL1: sub_payment_rule_start_dttm | AM1: sub_repricing_rule_start_dttm | AN1: sub_repricing_rule_period_cd | AO1: sub_repricing_rule_day_num | AP1: sub_cap_limit_interest_rate | AQ1: sub_floor_limit_interest_rate | AR1: sub_coeff_index | AS1: deal_report_dttm | AT1: sub_repricing_rule_first_event_flg | AU1: indicator_lag_cd | AV1: sub_indicator_lag_cd | AW1: Столбец1
A2: Дата, на которую выполняется расчет | B2: Код, по которому выбирается способ построения платежей | C2: Номер сделки | E2: Первоначальная сумма основного долга | F2: Остаток основного долга на дату расчёта | G2: Дата начала сделки | H2: Дата окончания сделки | J2: Процентная ставка | L2: код базового процентного индикатора, к которому привязана плавающая ставка сделки | M2: Начальная дата правила выплаты процентов | N2: Периодичность выплаты процентов | O2: День месяца для выплаты | P2: правило подсчёта времени для начисления процентов | Q2: Начальная дата правила, от которой строится расписание регулярных платежей. | R2: Периодичность регулярных платежей | U2: код периодичности пересмотра процентной ставки по сделке | X2: категория банковского продукта, к которому относится сделка | Y2: код модели поведения клиентов | Z2: Явно перечисленные даты выплаты процентов | AA2: Явно перечисленные даты и суммы возврата основного долга
A3: 44804 | B3: ANN | C3: 1 | D3: RUB | F3: 3646037.9 | G3: 44004 | H3: 54954 | I3: FIXED | J3: 0.075 | P3: ACT/ACT | Q3: 44004 | R3: 1M | Y3: PREPAYMENT_CONSUMER | AS3: 44804
A5: бакеты | B5: 1d | C5: 1m | D5: 3m | E5: 6m | F5: 9m | G5: 1y | I5: 1.5y | J5: 2y | K5: 3y | L5: 4y | M5: 5y | N5: 6y | O5: 7y | P5: 8y | Q5: 9y | R5: 10y | S5: 15y | T5: 20y | U5: 30y
A6: тенор | B6: 0.0028 | C6: 0.0417 | D6: 0.1667 | E6: 0.375 | F6: 0.625 | G6: 0.875 | I6: 1.25 | J6: 1.75 | K6: 2.5 | L6: 3.5 | M6: 4.5 | N6: 5.5 | O6: 6.5 | P6: 7.5 | Q6: 8.5 | R6: 9.5 | S6: 12.5 | T6: 17.5 | U6: 25
A9: Дисконтированный денежный поток в базовом сценарии | B9: 0.99965117 | C9: 0.99481748 | D9: 0.97944273 | E9: 0.95425355 | F9: 0.92421096 | G9: 0.89421844 | I9: 0.84855205 | J9: 0.78962766 | K9: 0.70449484 | L9: 0.60665028 | M9: 0.51960779 | N9: 0.44374038 | O9: 0.38279881 | P9: 0.32979972 | Q9: 0.28404048 | R9: 0.24334737 | S9: 0.15423917 | T9: 0.072259135 | U9: 0.022739113
A11: Дисконтированный денежный поток в стрессовом сценарии | B11: 0.99973255 | C11: 0.99600261 | D11: 0.9838458 | E11: 0.96298085 | F11: 0.93658931 | G11: 0.90879806 | I11: 0.86418246 | J11: 0.80360267 | K11: 0.71197219 | L11: 0.60262401 | M11: 0.50435485 | N11: 0.4193907 | O11: 0.35155591 | P11: 0.2940455 | Q11: 0.24580293 | R11: 0.20445748 | S11: 0.11895426 | T11: 0.048877239 | U11: 0.012844722
A14: Суммарная ежемесячная выплата | B14: =IF($J$3=0,$F$3/$B$15,$F$3*($J$3*0.0833333333333333)/(1-(1+$J$3*0.0833333333333333)^(-$B$15))) -> 26037.322
A15: До окончания сделки с даты рассчета | B15: 334
B17: 44795 | F17: =F3*J3/12*(1+J3/12)^334/((1+J3/12)^334-1) -> 26037.322 | G17: =F3*J3/12 -> 22787.737 | H17: =F3*J3*(31/365) -> 23224.762
B18: Даты будущих платежей | C18: Платеж | D18: Суммы возврата основного долга | E18: Остаток долга после каждого погашения | F18: Суммы процентов | G18: Общий денежный поток | H18: Дней до выплат | I18: Бакет | J18: Текущая стоимость каждого потока в базовом сценарии | K18: Суммарная текущая стоимость сделки в базовом сценарии | L18: Текущая стоимость каждого потока в стрессовом сценарии | M18: Суммарная текущая стоимость сделки в стрессовом сценарии | N18: Изменение стоимости — dNPV
A19: PRINCIPAL / INTEREST | B19: 44826 | D19: =$B$14-F19 -> 2812.5601 | E19: =$F$3-D19 -> 3643225.3 | F19: =$F$3*$J$3*((B19-B17)/365) -> 23224.762 | G19: =SUM(D19,F19) -> 26037.322 | H19: =B19-$A$3 -> 22 | I19: =$C$5 -> 1m | J19: =G19*$C$9 -> 25902.383 | L19: =G19*$C$11 -> 25933.241
A20: PRINCIPAL / INTEREST | B20: 44856 | D20: =$B$14-F20 -> 3579.0837 | E20: =E19-D20 -> 3639646.2 | F20: =E19*$J$3*((B20-B19)/365) -> 22458.238 | G20: =SUM(D20,F20) -> 26037.322 | H20: =B20-$A$3 -> 52 | I20: =$D$5 -> 3m | J20: =G20*$D$9 -> 25502.066 | L20: =G20*$D$11 -> 25616.71
A21: PRINCIPAL / INTEREST | B21: 44887 | D21: =$B$14-F21 -> 2853.274 | E21: =E20-D21 -> 3636793 | F21: =E20*$J$3*((B21-B20)/365) -> 23184.048 | G21: =SUM(D21,F21) -> 26037.322 | H21: =B21-$A$3 -> 83 | I21: =$D$5 -> 3m | J21: =G21*$D$9 -> 25502.066 | L21: =G21*$D$11 -> 25616.71
A22: PRINCIPAL / INTEREST | B22: 44917 | D22: =$B$14-F22 -> 3618.7352 | E22: =E21-D22 -> 3633174.2 | F22: =E21*$J$3*((B22-B21)/365) -> 22418.587 | G22: =SUM(D22,F22) -> 26037.322 | H22: =B22-$A$3 -> 113 | I22: =$E$5 -> 6m | J22: =G22*$E$9 -> 24846.207 | L22: =G22*$E$11 -> 25073.443
A23: PRINCIPAL / INTEREST | B23: 44948 | D23: =$B$14-F23 -> 2894.4998 | E23: =E22-D23 -> 3630279.7 | F23: =E22*$J$3*((B23-B22)/365) -> 23142.822 | G23: =SUM(D23,F23) -> 26037.322 | H23: =B23-$A$3 -> 144 | I23: =$E$5 -> 6m | J23: =G23*$E$9 -> 24846.207 | L23: =G23*$E$11 -> 25073.443
A24: PRINCIPAL / INTEREST | B24: 44979 | D24: =$B$14-F24 -> 2912.9374 | E24: =E23-D24 -> 3627366.8 | F24: =E23*$J$3*((B24-B23)/365) -> 23124.385 | G24: =SUM(D24,F24) -> 26037.322 | H24: =B24-$A$3 -> 175 | I24: =$E$5 -> 6m | J24: =G24*$E$9 -> 24846.207 | L24: =G24*$E$11 -> 25073.443
A25: PRINCIPAL / INTEREST | B25: 45007 | D25: =$B$14-F25 -> 5167.5404 | E25: =E24-D25 -> 3622199.3 | F25: =E24*$J$3*((B25-B24)/365) -> 20869.782 | G25: =SUM(D25,F25) -> 26037.322 | H25: =B25-$A$3 -> 203 | I25: =$F$5 -> 9m | J25: =G25*$F$9 -> 24063.978 | L25: =G25*$F$11 -> 24386.278
A26: PRINCIPAL / INTEREST | B26: 45038 | D26: =$B$14-F26 -> 2964.4089 | E26: =E25-D26 -> 3619234.9 | F26: =E25*$J$3*((B26-B25)/365) -> 23072.913 | G26: =SUM(D26,F26) -> 26037.322 | H26: =B26-$A$3 -> 234 | I26: =$F$5 -> 9m | J26: =G26*$F$9 -> 24063.978 | L26: =G26*$F$11 -> 24386.278
A27: PRINCIPAL / INTEREST | B27: 45068 | D27: =$B$14-F27 -> 3726.9702 | E27: =E26-D27 -> 3615507.9 | F27: =E26*$J$3*((B27-B26)/365) -> 22310.352 | G27: =SUM(D27,F27) -> 26037.322 | H27: =B27-$A$3 -> 264 | I27: =$F$5 -> 9m | J27: =G27*$F$9 -> 24063.978 | L27: =G27*$F$11 -> 24386.278
A28: PRINCIPAL / INTEREST | B28: 45099 | D28: =$B$14-F28 -> 3007.0321 | E28: =E27-D28 -> 3612500.8 | F28: =E27*$J$3*((B28-B27)/365) -> 23030.29 | G28: =SUM(D28,F28) -> 26037.322 | H28: =B28-$A$3 -> 295 | I28: =$G$5 -> 1y | J28: =G28*$G$9 -> 23283.053 | L28: =G28*$G$11 -> 23662.668
A29: PRINCIPAL / INTEREST | B29: 45129 | D29: =$B$14-F29 -> 3768.4812 | E29: =E28-D29 -> 3608732.4 | F29: =E28*$J$3*((B29-B28)/365) -> 22268.841 | G29: =SUM(D29,F29) -> 26037.322 | H29: =B29-$A$3 -> 325 | I29: =$G$5 -> 1y | J29: =G29*$G$9 -> 23283.053 | L29: =G29*$G$11 -> 23662.668
A30: PRINCIPAL / INTEREST | B30: 45160 | D30: =$B$14-F30 -> 3050.1912 | E30: =E29-D30 -> 3605682.2 | F30: =E29*$J$3*((B30-B29)/365) -> 22987.131 | G30: =SUM(D30,F30) -> 26037.322 | H30: =B30-$A$3 -> 356 | I30: =$G$5 -> 1y | J30: =G30*$G$9 -> 23283.053 | L30: =G30*$G$11 -> 23662.668
A31: PRINCIPAL / INTEREST | B31: 45191 | D31: =$B$14-F31 -> 3069.6205 | E31: =E30-D31 -> 3602612.6 | F31: =E30*$J$3*((B31-B30)/365) -> 22967.702 | G31: =SUM(D31,F31) -> 26037.322 | H31: =B31-$A$3 -> 387 | I31: =$I$5 -> 1.5y | J31: =G31*$I$9 -> 22094.023 | L31: =G31*$I$11 -> 22500.997
A32: PRINCIPAL / INTEREST | B32: 45221 | D32: =$B$14-F32 -> 3829.4364 | E32: =E31-D32 -> 3598783.1 | F32: =E31*$J$3*((B32-B31)/365) -> 22207.886 | G32: =SUM(D32,F32) -> 26037.322 | H32: =B32-$A$3 -> 417 | I32: =$I$5 -> 1.5y | J32: =G32*$I$9 -> 22094.023 | L32: =G32*$I$11 -> 22500.997
A33: PRINCIPAL / INTEREST | B33: 45252 | D33: =$B$14-F33 -> 3113.5665 | E33: =E32-D33 -> 3595669.6 | F33: =E32*$J$3*((B33-B32)/365) -> 22923.755 | G33: =SUM(D33,F33) -> 26037.322 | H33: =B33-$A$3 -> 448 | I33: =$I$5 -> 1.5y | J33: =G33*$I$9 -> 22094.023 | L33: =G33*$I$11 -> 22500.997
A34: PRINCIPAL / INTEREST | B34: 45282 | D34: =$B$14-F34 -> 3872.2357 | E34: =E33-D34 -> 3591797.3 | F34: =E33*$J$3*((B34-B33)/365) -> 22165.086 | G34: =SUM(D34,F34) -> 26037.322 | H34: =B34-$A$3 -> 478 | I34: =$I$5 -> 1.5y | J34: =G34*$I$9 -> 22094.023 | L34: =G34*$I$11 -> 22500.997
A35: PRINCIPAL / INTEREST | B35: 45313 | D35: =$B$14-F35 -> 3158.0651 | E35: =E34-D35 -> 3588639.3 | F35: =E34*$J$3*((B35-B34)/365) -> 22879.257 | G35: =SUM(D35,F35) -> 26037.322 | H35: =B35-$A$3 -> 509 | I35: =$I$5 -> 1.5y | J35: =G35*$I$9 -> 22094.023 | L35: =G35*$I$11 -> 22500.997
A36: PRINCIPAL / INTEREST | B36: 45344 | D36: =$B$14-F36 -> 3178.1816 | E36: =E35-D36 -> 3585461.1 | F36: =E35*$J$3*((B36-B35)/365) -> 22859.14 | G36: =SUM(D36,F36) -> 26037.322 | H36: =B36-$A$3 -> 540 | I36: =$I$5 -> 1.5y | J36: =G36*$I$9 -> 22094.023 | L36: =G36*$I$11 -> 22500.997
A37: PRINCIPAL / INTEREST | B37: 45373 | D37: =$B$14-F37 -> 4671.9033 | E37: =E36-D37 -> 3580789.2 | F37: =E36*$J$3*((B37-B36)/365) -> 21365.419 | G37: =SUM(D37,F37) -> 26037.322 | H37: =B37-$A$3 -> 569 | I37: =$J$5 -> 2y | J37: =G37*$J$9 -> 20559.79 | L37: =G37*$J$11 -> 20923.661
A38: PRINCIPAL / INTEREST | B38: 45404 | D38: =$B$14-F38 -> 3228.1855 | E38: =E37-D38 -> 3577561 | F38: =E37*$J$3*((B38-B37)/365) -> 22809.136 | G38: =SUM(D38,F38) -> 26037.322 | H38: =B38-$A$3 -> 600 | I38: =$J$5 -> 2y | J38: =G38*$J$9 -> 20559.79 | L38: =G38*$J$11 -> 20923.661
A39: PRINCIPAL / INTEREST | B39: 45434 | D39: =$B$14-F39 -> 3983.8639 | E39: =E38-D39 -> 3573577.1 | F39: =E38*$J$3*((B39-B38)/365) -> 22053.458 | G39: =SUM(D39,F39) -> 26037.322 | H39: =B39-$A$3 -> 630 | I39: =$J$5 -> 2y | J39: =G39*$J$9 -> 20559.79 | L39: =G39*$J$11 -> 20923.661
A40: PRINCIPAL / INTEREST | B40: 45465 | D40: =$B$14-F40 -> 3274.1253 | E40: =E39-D40 -> 3570303 | F40: =E39*$J$3*((B40-B39)/365) -> 22763.197 | G40: =SUM(D40,F40) -> 26037.322 | H40: =B40-$A$3 -> 661 | I40: =$J$5 -> 2y | J40: =G40*$J$9 -> 20559.79 | L40: =G40*$J$11 -> 20923.661
A41: PRINCIPAL / INTEREST | B41: 45495 | D41: =$B$14-F41 -> 4028.6049 | E41: =E40-D41 -> 3566274.4 | F41: =E40*$J$3*((B41-B40)/365) -> 22008.717 | G41: =SUM(D41,F41) -> 26037.322 | H41: =B41-$A$3 -> 691 | I41: =$J$5 -> 2y | J41: =G41*$J$9 -> 20559.79 | L41: =G41*$J$11 -> 20923.661
A42: PRINCIPAL / INTEREST | B42: 45526 | D42: =$B$14-F42 -> 3320.6427 | E42: =E41-D42 -> 3562953.7 | F42: =E41*$J$3*((B42-B41)/365) -> 22716.679 | G42: =SUM(D42,F42) -> 26037.322 | H42: =B42-$A$3 -> 722 | I42: =$J$5 -> 2y | J42: =G42*$J$9 -> 20559.79 | L42: =G42*$J$11 -> 20923.661
A43: PRINCIPAL / INTEREST | B43: 45557 | D43: =$B$14-F43 -> 3341.7947 | E43: =E42-D43 -> 3559611.9 | F43: =E42*$J$3*((B43-B42)/365) -> 22695.527 | G43: =SUM(D43,F43) -> 26037.322 | H43: =B43-$A$3 -> 753 | I43: =$K$5 -> 3y | J43: =G43*$K$9 -> 18343.159 | L43: =G43*$K$11 -> 18537.849
A44: PRINCIPAL / INTEREST | B44: 45587 | D44: =$B$14-F44 -> 4094.5086 | E44: =E43-D44 -> 3555517.4 | F44: =E43*$J$3*((B44-B43)/365) -> 21942.813 | G44: =SUM(D44,F44) -> 26037.322 | H44: =B44-$A$3 -> 783 | I44: =$K$5 -> 3y | J44: =G44*$K$9 -> 18343.159 | L44: =G44*$K$11 -> 18537.849
A45: PRINCIPAL / INTEREST | B45: 45618 | D45: =$B$14-F45 -> 3389.163 | E45: =E44-D45 -> 3552128.3 | F45: =E44*$J$3*((B45-B44)/365) -> 22648.159 | G45: =SUM(D45,F45) -> 26037.322 | H45: =B45-$A$3 -> 814 | I45: =$K$5 -> 3y | J45: =G45*$K$9 -> 18343.159 | L45: =G45*$K$11 -> 18537.849
A46: PRINCIPAL / INTEREST | B46: 45648 | D46: =$B$14-F46 -> 4140.6408 | E46: =E45-D46 -> 3547987.6 | F46: =E45*$J$3*((B46-B45)/365) -> 21896.681 | G46: =SUM(D46,F46) -> 26037.322 | H46: =B46-$A$3 -> 844 | I46: =$K$5 -> 3y | J46: =G46*$K$9 -> 18343.159 | L46: =G46*$K$11 -> 18537.849
A47: PRINCIPAL / INTEREST | B47: 45679 | D47: =$B$14-F47 -> 3437.1268 | E47: =E46-D47 -> 3544550.5 | F47: =E46*$J$3*((B47-B46)/365) -> 22600.195 | G47: =SUM(D47,F47) -> 26037.322 | H47: =B47-$A$3 -> 875 | I47: =$K$5 -> 3y | J47: =G47*$K$9 -> 18343.159 | L47: =G47*$K$11 -> 18537.849
A48: PRINCIPAL / INTEREST | B48: 45710 | D48: =$B$14-F48 -> 3459.0208 | E48: =E47-D48 -> 3541091.5 | F48: =E47*$J$3*((B48-B47)/365) -> 22578.301 | G48: =SUM(D48,F48) -> 26037.322 | H48: =B48-$A$3 -> 906 | I48: =$K$5 -> 3y | J48: =G48*$K$9 -> 18343.159 | L48: =G48*$K$11 -> 18537.849
A49: PRINCIPAL / INTEREST | B49: 45738 | D49: =$B$14-F49 -> 5663.9189 | E49: =E48-D49 -> 3535427.6 | F49: =E48*$J$3*((B49-B48)/365) -> 20373.403 | G49: =SUM(D49,F49) -> 26037.322 | H49: =B49-$A$3 -> 934 | I49: =$K$5 -> 3y | J49: =G49*$K$9 -> 18343.159 | L49: =G49*$K$11 -> 18537.849
A50: PRINCIPAL / INTEREST | B50: 45769 | D50: =$B$14-F50 -> 3517.1327 | E50: =E49-D50 -> 3531910.4 | F50: =E49*$J$3*((B50-B49)/365) -> 22520.189 | G50: =SUM(D50,F50) -> 26037.322 | H50: =B50-$A$3 -> 965 | I50: =$K$5 -> 3y | J50: =G50*$K$9 -> 18343.159 | L50: =G50*$K$11 -> 18537.849
A51: PRINCIPAL / INTEREST | B51: 45799 | D51: =$B$14-F51 -> 4265.2714 | E51: =E50-D51 -> 3527645.2 | F51: =E50*$J$3*((B51-B50)/365) -> 21772.051 | G51: =SUM(D51,F51) -> 26037.322 | H51: =B51-$A$3 -> 995 | I51: =$K$5 -> 3y | J51: =G51*$K$9 -> 18343.159 | L51: =G51*$K$11 -> 18537.849
A52: PRINCIPAL / INTEREST | B52: 45830 | D52: =$B$14-F52 -> 3566.7055 | E52: =E51-D52 -> 3524078.5 | F52: =E51*$J$3*((B52-B51)/365) -> 22470.616 | G52: =SUM(D52,F52) -> 26037.322 | H52: =B52-$A$3 -> 1026 | I52: =$K$5 -> 3y | J52: =G52*$K$9 -> 18343.159 | L52: =G52*$K$11 -> 18537.849
A53: PRINCIPAL / INTEREST | B53: 45860 | D53: =$B$14-F53 -> 4313.5507 | E53: =E52-D53 -> 3519764.9 | F53: =E52*$J$3*((B53-B52)/365) -> 21723.771 | G53: =SUM(D53,F53) -> 26037.322 | H53: =B53-$A$3 -> 1056 | I53: =$K$5 -> 3y | J53: =G53*$K$9 -> 18343.159 | L53: =G53*$K$11 -> 18537.849
A54: PRINCIPAL / INTEREST | B54: 45891 | D54: =$B$14-F54 -> 3616.9017 | E54: =E53-D54 -> 3516148 | F54: =E53*$J$3*((B54-B53)/365) -> 22420.42 | G54: =SUM(D54,F54) -> 26037.322 | H54: =B54-$A$3 -> 1087 | I54: =$K$5 -> 3y | J54: =G54*$K$9 -> 18343.159 | L54: =G54*$K$11 -> 18537.849
A55: PRINCIPAL / INTEREST | B55: 45922 | D55: =$B$14-F55 -> 3639.9408 | E55: =E54-D55 -> 3512508.1 | F55: =E54*$J$3*((B55-B54)/365) -> 22397.381 | G55: =SUM(D55,F55) -> 26037.322 | H55: =B55-$A$3 -> 1118 | I55: =$L$5 -> 4y | J55: =G55*$L$9 -> 15795.549 | L55: =G55*$L$11 -> 15690.715
A56: PRINCIPAL / INTEREST | B56: 45952 | D56: =$B$14-F56 -> 4384.875 | E56: =E55-D56 -> 3508123.2 | F56: =E55*$J$3*((B56-B55)/365) -> 21652.447 | G56: =SUM(D56,F56) -> 26037.322 | H56: =B56-$A$3 -> 1148 | I56: =$L$5 -> 4y | J56: =G56*$L$9 -> 15795.549 | L56: =G56*$L$11 -> 15690.715
A57: PRINCIPAL / INTEREST | B57: 45983 | D57: =$B$14-F57 -> 3691.0578 | E57: =E56-D57 -> 3504432.1 | F57: =E56*$J$3*((B57-B56)/365) -> 22346.264 | G57: =SUM(D57,F57) -> 26037.322 | H57: =B57-$A$3 -> 1179 | I57: =$L$5 -> 4y | J57: =G57*$L$9 -> 15795.549 | L57: =G57*$L$11 -> 15690.715
A58: PRINCIPAL / INTEREST | B58: 46013 | D58: =$B$14-F58 -> 4434.6582 | E58: =E57-D58 -> 3499997.5 | F58: =E57*$J$3*((B58-B57)/365) -> 21602.664 | G58: =SUM(D58,F58) -> 26037.322 | H58: =B58-$A$3 -> 1209 | I58: =$L$5 -> 4y | J58: =G58*$L$9 -> 15795.549 | L58: =G58*$L$11 -> 15690.715
A59: PRINCIPAL / INTEREST | B59: 46044 | D59: =$B$14-F59 -> 3742.8175 | E59: =E58-D59 -> 3496254.7 | F59: =E58*$J$3*((B59-B58)/365) -> 22294.504 | G59: =SUM(D59,F59) -> 26037.322 | H59: =B59-$A$3 -> 1240 | I59: =$L$5 -> 4y | J59: =G59*$L$9 -> 15795.549 | L59: =G59*$L$11 -> 15690.715
A60: PRINCIPAL / INTEREST | B60: 46075 | D60: =$B$14-F60 -> 3766.6588 | E60: =E59-D60 -> 3492488 | F60: =E59*$J$3*((B60-B59)/365) -> 22270.663 | G60: =SUM(D60,F60) -> 26037.322 | H60: =B60-$A$3 -> 1271 | I60: =$L$5 -> 4y | J60: =G60*$L$9 -> 15795.549 | L60: =G60*$L$11 -> 15690.715
A61: PRINCIPAL / INTEREST | B61: 46103 | D61: =$B$14-F61 -> 5943.5554 | E61: =E60-D61 -> 3486544.4 | F61: =E60*$J$3*((B61-B60)/365) -> 20093.767 | G61: =SUM(D61,F61) -> 26037.322 | H61: =B61-$A$3 -> 1299 | I61: =$L$5 -> 4y | J61: =G61*$L$9 -> 15795.549 | L61: =G61*$L$11 -> 15690.715
A62: PRINCIPAL / INTEREST | B62: 46134 | D62: =$B$14-F62 -> 3828.5115 | E62: =E61-D62 -> 3482715.9 | F62: =E61*$J$3*((B62-B61)/365) -> 22208.811 | G62: =SUM(D62,F62) -> 26037.322 | H62: =B62-$A$3 -> 1330 | I62: =$L$5 -> 4y | J62: =G62*$L$9 -> 15795.549 | L62: =G62*$L$11 -> 15690.715
A63: PRINCIPAL / INTEREST | B63: 46164 | D63: =$B$14-F63 -> 4568.5251 | E63: =E62-D63 -> 3478147.4 | F63: =E62*$J$3*((B63-B62)/365) -> 21468.797 | G63: =SUM(D63,F63) -> 26037.322 | H63: =B63-$A$3 -> 1360 | I63: =$L$5 -> 4y | J63: =G63*$L$9 -> 15795.549 | L63: =G63*$L$11 -> 15690.715
A64: PRINCIPAL / INTEREST | B64: 46195 | D64: =$B$14-F64 -> 3881.9995 | E64: =E63-D64 -> 3474265.4 | F64: =E63*$J$3*((B64-B63)/365) -> 22155.323 | G64: =SUM(D64,F64) -> 26037.322 | H64: =B64-$A$3 -> 1391 | I64: =$L$5 -> 4y | J64: =G64*$L$9 -> 15795.549 | L64: =G64*$L$11 -> 15690.715
A65: PRINCIPAL / INTEREST | B65: 46225 | D65: =$B$14-F65 -> 4620.6174 | E65: =E64-D65 -> 3469644.8 | F65: =E64*$J$3*((B65-B64)/365) -> 21416.705 | G65: =SUM(D65,F65) -> 26037.322 | H65: =B65-$A$3 -> 1421 | I65: =$L$5 -> 4y | J65: =G65*$L$9 -> 15795.549 | L65: =G65*$L$11 -> 15690.715
A66: PRINCIPAL / INTEREST | B66: 46256 | D66: =$B$14-F66 -> 3936.16 | E66: =E65-D66 -> 3465708.6 | F66: =E65*$J$3*((B66-B65)/365) -> 22101.162 | G66: =SUM(D66,F66) -> 26037.322 | H66: =B66-$A$3 -> 1452 | I66: =$L$5 -> 4y | J66: =G66*$L$9 -> 15795.549 | L66: =G66*$L$11 -> 15690.715
A67: PRINCIPAL / INTEREST | B67: 46287 | D67: =$B$14-F67 -> 3961.2328 | E67: =E66-D67 -> 3461747.4 | F67: =E66*$J$3*((B67-B66)/365) -> 22076.089 | G67: =SUM(D67,F67) -> 26037.322 | H67: =B67-$A$3 -> 1483 | I67: =$M$5 -> 5y | J67: =G67*$M$9 -> 13529.195 | L67: =G67*$M$11 -> 13132.05
A68: PRINCIPAL / INTEREST | B68: 46317 | D68: =$B$14-F68 -> 4697.7832 | E68: =E67-D68 -> 3457049.6 | F68: =E67*$J$3*((B68-B67)/365) -> 21339.539 | G68: =SUM(D68,F68) -> 26037.322 | H68: =B68-$A$3 -> 1513 | I68: =$M$5 -> 5y | J68: =G68*$M$9 -> 13529.195 | L68: =G68*$M$11 -> 13132.05
A69: PRINCIPAL / INTEREST | B69: 46348 | D69: =$B$14-F69 -> 4016.3895 | E69: =E68-D69 -> 3453033.2 | F69: =E68*$J$3*((B69-B68)/365) -> 22020.932 | G69: =SUM(D69,F69) -> 26037.322 | H69: =B69-$A$3 -> 1544 | I69: =$M$5 -> 5y | J69: =G69*$M$9 -> 13529.195 | L69: =G69*$M$11 -> 13132.05
A70: PRINCIPAL / INTEREST | B70: 46378 | D70: =$B$14-F70 -> 4751.5007 | E70: =E69-D70 -> 3448281.7 | F70: =E69*$J$3*((B70-B69)/365) -> 21285.821 | G70: =SUM(D70,F70) -> 26037.322 | H70: =B70-$A$3 -> 1574 | I70: =$M$5 -> 5y | J70: =G70*$M$9 -> 13529.195 | L70: =G70*$M$11 -> 13132.05
A71: PRINCIPAL / INTEREST | B71: 46409 | D71: =$B$14-F71 -> 4072.2398 | E71: =E70-D71 -> 3444209.5 | F71: =E70*$J$3*((B71-B70)/365) -> 21965.082 | G71: =SUM(D71,F71) -> 26037.322 | H71: =B71-$A$3 -> 1605 | I71: =$M$5 -> 5y | J71: =G71*$M$9 -> 13529.195 | L71: =G71*$M$11 -> 13132.05
A72: PRINCIPAL / INTEREST | B72: 46440 | D72: =$B$14-F72 -> 4098.1794 | E72: =E71-D72 -> 3440111.3 | F72: =E71*$J$3*((B72-B71)/365) -> 21939.143 | G72: =SUM(D72,F72) -> 26037.322 | H72: =B72-$A$3 -> 1636 | I72: =$M$5 -> 5y | J72: =G72*$M$9 -> 13529.195 | L72: =G72*$M$11 -> 13132.05
A73: PRINCIPAL / INTEREST | B73: 46468 | D73: =$B$14-F73 -> 6244.9008 | E73: =E72-D73 -> 3433866.4 | F73: =E72*$J$3*((B73-B72)/365) -> 19792.421 | G73: =SUM(D73,F73) -> 26037.322 | H73: =B73-$A$3 -> 1664 | I73: =$M$5 -> 5y | J73: =G73*$M$9 -> 13529.195 | L73: =G73*$M$11 -> 13132.05
A74: PRINCIPAL / INTEREST | B74: 46499 | D74: =$B$14-F74 -> 4164.0634 | E74: =E73-D74 -> 3429702.3 | F74: =E73*$J$3*((B74-B73)/365) -> 21873.259 | G74: =SUM(D74,F74) -> 26037.322 | H74: =B74-$A$3 -> 1695 | I74: =$M$5 -> 5y | J74: =G74*$M$9 -> 13529.195 | L74: =G74*$M$11 -> 13132.05
A75: PRINCIPAL / INTEREST | B75: 46529 | D75: =$B$14-F75 -> 4895.3213 | E75: =E74-D75 -> 3424807 | F75: =E74*$J$3*((B75-B74)/365) -> 21142.001 | G75: =SUM(D75,F75) -> 26037.322 | H75: =B75-$A$3 -> 1725 | I75: =$M$5 -> 5y | J75: =G75*$M$9 -> 13529.195 | L75: =G75*$M$11 -> 13132.05
A76: PRINCIPAL / INTEREST | B76: 46560 | D76: =$B$14-F76 -> 4221.7704 | E76: =E75-D76 -> 3420585.3 | F76: =E75*$J$3*((B76-B75)/365) -> 21815.552 | G76: =SUM(D76,F76) -> 26037.322 | H76: =B76-$A$3 -> 1756 | I76: =$M$5 -> 5y | J76: =G76*$M$9 -> 13529.195 | L76: =G76*$M$11 -> 13132.05
A77: PRINCIPAL / INTEREST | B77: 46590 | D77: =$B$14-F77 -> 4951.5225 | E77: =E76-D77 -> 3415633.7 | F77: =E76*$J$3*((B77-B76)/365) -> 21085.799 | G77: =SUM(D77,F77) -> 26037.322 | H77: =B77-$A$3 -> 1786 | I77: =$M$5 -> 5y | J77: =G77*$M$9 -> 13529.195 | L77: =G77*$M$11 -> 13132.05
A78: PRINCIPAL / INTEREST | B78: 46621 | D78: =$B$14-F78 -> 4280.203 | E78: =E77-D78 -> 3411353.5 | F78: =E77*$J$3*((B78-B77)/365) -> 21757.119 | G78: =SUM(D78,F78) -> 26037.322 | H78: =B78-$A$3 -> 1817 | I78: =$M$5 -> 5y | J78: =G78*$M$9 -> 13529.195 | L78: =G78*$M$11 -> 13132.05
A79: PRINCIPAL / INTEREST | B79: 46652 | D79: =$B$14-F79 -> 4307.4674 | E79: =E78-D79 -> 3407046.1 | F79: =E78*$J$3*((B79-B78)/365) -> 21729.855 | G79: =SUM(D79,F79) -> 26037.322 | H79: =B79-$A$3 -> 1848 | I79: =$N$5 -> 6y | J79: =G79*$N$9 -> 11553.811 | L79: =G79*$N$11 -> 10919.811
A80: PRINCIPAL / INTEREST | B80: 46682 | D80: =$B$14-F80 -> 5034.9833 | E80: =E79-D80 -> 3402011.1 | F80: =E79*$J$3*((B80-B79)/365) -> 21002.339 | G80: =SUM(D80,F80) -> 26037.322 | H80: =B80-$A$3 -> 1878 | I80: =$N$5 -> 6y | J80: =G80*$N$9 -> 11553.811 | L80: =G80*$N$11 -> 10919.811
A81: PRINCIPAL / INTEREST | B81: 46713 | D81: =$B$14-F81 -> 4366.9775 | E81: =E80-D81 -> 3397644.1 | F81: =E80*$J$3*((B81-B80)/365) -> 21670.345 | G81: =SUM(D81,F81) -> 26037.322 | H81: =B81-$A$3 -> 1909 | I81: =$N$5 -> 6y | J81: =G81*$N$9 -> 11553.811 | L81: =G81*$N$11 -> 10919.811
A82: PRINCIPAL / INTEREST | B82: 46743 | D82: =$B$14-F82 -> 5092.9406 | E82: =E81-D82 -> 3392551.2 | F82: =E81*$J$3*((B82-B81)/365) -> 20944.381 | G82: =SUM(D82,F82) -> 26037.322 | H82: =B82-$A$3 -> 1939 | I82: =$N$5 -> 6y | J82: =G82*$N$9 -> 11553.811 | L82: =G82*$N$11 -> 10919.811
A83: PRINCIPAL / INTEREST | B83: 46774 | D83: =$B$14-F83 -> 4427.2359 | E83: =E82-D83 -> 3388123.9 | F83: =E82*$J$3*((B83-B82)/365) -> 21610.086 | G83: =SUM(D83,F83) -> 26037.322 | H83: =B83-$A$3 -> 1970 | I83: =$N$5 -> 6y | J83: =G83*$N$9 -> 11553.811 | L83: =G83*$N$11 -> 10919.811
A84: PRINCIPAL / INTEREST | B84: 46805 | D84: =$B$14-F84 -> 4455.4368 | E84: =E83-D84 -> 3383668.5 | F84: =E83*$J$3*((B84-B83)/365) -> 21581.885 | G84: =SUM(D84,F84) -> 26037.322 | H84: =B84-$A$3 -> 2001 | I84: =$N$5 -> 6y | J84: =G84*$N$9 -> 11553.811 | L84: =G84*$N$11 -> 10919.811
A85: PRINCIPAL / INTEREST | B85: 46834 | D85: =$B$14-F85 -> 5874.366 | E85: =E84-D85 -> 3377794.1 | F85: =E84*$J$3*((B85-B84)/365) -> 20162.956 | G85: =SUM(D85,F85) -> 26037.322 | H85: =B85-$A$3 -> 2030 | I85: =$N$5 -> 6y | J85: =G85*$N$9 -> 11553.811 | L85: =G85*$N$11 -> 10919.811
A86: PRINCIPAL / INTEREST | B86: 46865 | D86: =$B$14-F86 -> 4521.2362 | E86: =E85-D86 -> 3373272.9 | F86: =E85*$J$3*((B86-B85)/365) -> 21516.086 | G86: =SUM(D86,F86) -> 26037.322 | H86: =B86-$A$3 -> 2061 | I86: =$N$5 -> 6y | J86: =G86*$N$9 -> 11553.811 | L86: =G86*$N$11 -> 10919.811
A87: PRINCIPAL / INTEREST | B87: 46895 | D87: =$B$14-F87 -> 5243.1741 | E87: =E86-D87 -> 3368029.7 | F87: =E86*$J$3*((B87-B86)/365) -> 20794.148 | G87: =SUM(D87,F87) -> 26037.322 | H87: =B87-$A$3 -> 2091 | I87: =$N$5 -> 6y | J87: =G87*$N$9 -> 11553.811 | L87: =G87*$N$11 -> 10919.811
A88: PRINCIPAL / INTEREST | B88: 46926 | D88: =$B$14-F88 -> 4583.4341 | E88: =E87-D88 -> 3363446.3 | F88: =E87*$J$3*((B88-B87)/365) -> 21453.888 | G88: =SUM(D88,F88) -> 26037.322 | H88: =B88-$A$3 -> 2122 | I88: =$N$5 -> 6y | J88: =G88*$N$9 -> 11553.811 | L88: =G88*$N$11 -> 10919.811
A89: PRINCIPAL / INTEREST | B89: 46956 | D89: =$B$14-F89 -> 5303.7491 | E89: =E88-D89 -> 3358142.5 | F89: =E88*$J$3*((B89-B88)/365) -> 20733.573 | G89: =SUM(D89,F89) -> 26037.322 | H89: =B89-$A$3 -> 2152 | I89: =$N$5 -> 6y | J89: =G89*$N$9 -> 11553.811 | L89: =G89*$N$11 -> 10919.811
A90: PRINCIPAL / INTEREST | B90: 46987 | D90: =$B$14-F90 -> 4646.4141 | E90: =E89-D90 -> 3353496.1 | F90: =E89*$J$3*((B90-B89)/365) -> 21390.908 | G90: =SUM(D90,F90) -> 26037.322 | H90: =B90-$A$3 -> 2183 | I90: =$N$5 -> 6y | J90: =G90*$N$9 -> 11553.811 | L90: =G90*$N$11 -> 10919.811
A91: PRINCIPAL / INTEREST | B91: 47018 | D91: =$B$14-F91 -> 4676.0112 | E91: =E90-D91 -> 3348820.1 | F91: =E90*$J$3*((B91-B90)/365) -> 21361.311 | G91: =SUM(D91,F91) -> 26037.322 | H91: =B91-$A$3 -> 2214 | I91: =$O$5 -> 7y | J91: =G91*$O$9 -> 9967.0559 | L91: =G91*$O$11 -> 9153.5745
A92: PRINCIPAL / INTEREST | B92: 47048 | D92: =$B$14-F92 -> 5393.9104 | E92: =E91-D92 -> 3343426.2 | F92: =E91*$J$3*((B92-B91)/365) -> 20643.412 | G92: =SUM(D92,F92) -> 26037.322 | H92: =B92-$A$3 -> 2244 | I92: =$O$5 -> 7y | J92: =G92*$O$9 -> 9967.0559 | L92: =G92*$O$11 -> 9153.5745
A93: PRINCIPAL / INTEREST | B93: 47079 | D93: =$B$14-F93 -> 4740.1552 | E93: =E92-D93 -> 3338686 | F93: =E92*$J$3*((B93-B92)/365) -> 21297.167 | G93: =SUM(D93,F93) -> 26037.322 | H93: =B93-$A$3 -> 2275 | I93: =$O$5 -> 7y | J93: =G93*$O$9 -> 9967.0559 | L93: =G93*$O$11 -> 9153.5745
A94: PRINCIPAL / INTEREST | B94: 47109 | D94: =$B$14-F94 -> 5456.3807 | E94: =E93-D94 -> 3333229.7 | F94: =E93*$J$3*((B94-B93)/365) -> 20580.941 | G94: =SUM(D94,F94) -> 26037.322 | H94: =B94-$A$3 -> 2305 | I94: =$O$5 -> 7y | J94: =G94*$O$9 -> 9967.0559 | L94: =G94*$O$11 -> 9153.5745
A95: PRINCIPAL / INTEREST | B95: 47140 | D95: =$B$14-F95 -> 4805.1057 | E95: =E94-D95 -> 3328424.5 | F95: =E94*$J$3*((B95-B94)/365) -> 21232.216 | G95: =SUM(D95,F95) -> 26037.322 | H95: =B95-$A$3 -> 2336 | I95: =$O$5 -> 7y | J95: =G95*$O$9 -> 9967.0559 | L95: =G95*$O$11 -> 9153.5745
A96: PRINCIPAL / INTEREST | B96: 47171 | D96: =$B$14-F96 -> 4835.7136 | E96: =E95-D96 -> 3323588.8 | F96: =E95*$J$3*((B96-B95)/365) -> 21201.608 | G96: =SUM(D96,F96) -> 26037.322 | H96: =B96-$A$3 -> 2367 | I96: =$O$5 -> 7y | J96: =G96*$O$9 -> 9967.0559 | L96: =G96*$O$11 -> 9153.5745
A97: PRINCIPAL / INTEREST | B97: 47199 | D97: =$B$14-F97 -> 6915.3041 | E97: =E96-D97 -> 3316673.5 | F97: =E96*$J$3*((B97-B96)/365) -> 19122.018 | G97: =SUM(D97,F97) -> 26037.322 | H97: =B97-$A$3 -> 2395 | I97: =$O$5 -> 7y | J97: =G97*$O$9 -> 9967.0559 | L97: =G97*$O$11 -> 9153.5745
A98: PRINCIPAL / INTEREST | B98: 47230 | D98: =$B$14-F98 -> 4910.566 | E98: =E97-D98 -> 3311763 | F98: =E97*$J$3*((B98-B97)/365) -> 21126.756 | G98: =SUM(D98,F98) -> 26037.322 | H98: =B98-$A$3 -> 2426 | I98: =$O$5 -> 7y | J98: =G98*$O$9 -> 9967.0559 | L98: =G98*$O$11 -> 9153.5745
A99: PRINCIPAL / INTEREST | B99: 47260 | D99: =$B$14-F99 -> 5622.3448 | E99: =E98-D99 -> 3306140.6 | F99: =E98*$J$3*((B99-B98)/365) -> 20414.977 | G99: =SUM(D99,F99) -> 26037.322 | H99: =B99-$A$3 -> 2456 | I99: =$O$5 -> 7y | J99: =G99*$O$9 -> 9967.0559 | L99: =G99*$O$11 -> 9153.5745
A100: PRINCIPAL / INTEREST | B100: 47291 | D100: =$B$14-F100 -> 4977.6592 | E100: =E99-D100 -> 3301163 | F100: =E99*$J$3*((B100-B99)/365) -> 21059.663 | G100: =SUM(D100,F100) -> 26037.322 | H100: =B100-$A$3 -> 2487 | I100: =$O$5 -> 7y | J100: =G100*$O$9 -> 9967.0559 | L100: =G100*$O$11 -> 9153.5745
A101: PRINCIPAL / INTEREST | B101: 47321 | D101: =$B$14-F101 -> 5687.6873 | E101: =E100-D101 -> 3295475.3 | F101: =E100*$J$3*((B101-B100)/365) -> 20349.635 | G101: =SUM(D101,F101) -> 26037.322 | H101: =B101-$A$3 -> 2517 | I101: =$O$5 -> 7y | J101: =G101*$O$9 -> 9967.0559 | L101: =G101*$O$11 -> 9153.5745
A102: PRINCIPAL / INTEREST | B102: 47352 | D102: =$B$14-F102 -> 5045.596 | E102: =E101-D102 -> 3290429.7 | F102: =E101*$J$3*((B102-B101)/365) -> 20991.726 | G102: =SUM(D102,F102) -> 26037.322 | H102: =B102-$A$3 -> 2548 | I102: =$O$5 -> 7y | J102: =G102*$O$9 -> 9967.0559 | L102: =G102*$O$11 -> 9153.5745
A103: PRINCIPAL / INTEREST | B103: 47383 | D103: =$B$14-F103 -> 5077.7357 | E103: =E102-D103 -> 3285351.9 | F103: =E102*$J$3*((B103-B102)/365) -> 20959.586 | G103: =SUM(D103,F103) -> 26037.322 | H103: =B103-$A$3 -> 2579 | I103: =$P$5 -> 8y | J103: =G103*$P$9 -> 8587.1014 | L103: =G103*$P$11 -> 7656.1574
A104: PRINCIPAL / INTEREST | B104: 47413 | D104: =$B$14-F104 -> 5785.1525 | E104: =E103-D104 -> 3279566.8 | F104: =E103*$J$3*((B104-B103)/365) -> 20252.169 | G104: =SUM(D104,F104) -> 26037.322 | H104: =B104-$A$3 -> 2609 | I104: =$P$5 -> 8y | J104: =G104*$P$9 -> 8587.1014 | L104: =G104*$P$11 -> 7656.1574
A105: PRINCIPAL / INTEREST | B105: 47444 | D105: =$B$14-F105 -> 5146.9308 | E105: =E104-D105 -> 3274419.9 | F105: =E104*$J$3*((B105-B104)/365) -> 20890.391 | G105: =SUM(D105,F105) -> 26037.322 | H105: =B105-$A$3 -> 2640 | I105: =$P$5 -> 8y | J105: =G105*$P$9 -> 8587.1014 | L105: =G105*$P$11 -> 7656.1574
A106: PRINCIPAL / INTEREST | B106: 47474 | D106: =$B$14-F106 -> 5852.5421 | E106: =E105-D106 -> 3268567.3 | F106: =E105*$J$3*((B106-B105)/365) -> 20184.78 | G106: =SUM(D106,F106) -> 26037.322 | H106: =B106-$A$3 -> 2670 | I106: =$P$5 -> 8y | J106: =G106*$P$9 -> 8587.1014 | L106: =G106*$P$11 -> 7656.1574
A107: PRINCIPAL / INTEREST | B107: 47505 | D107: =$B$14-F107 -> 5216.996 | E107: =E106-D107 -> 3263350.3 | F107: =E106*$J$3*((B107-B106)/365) -> 20820.326 | G107: =SUM(D107,F107) -> 26037.322 | H107: =B107-$A$3 -> 2701 | I107: =$P$5 -> 8y | J107: =G107*$P$9 -> 8587.1014 | L107: =G107*$P$11 -> 7656.1574
...
